[
  {
    "幢号": "1幢",
    "房号": "201",
    "面积（m²）": "124.32"
  },
  {
    "幢号": "1幢",
    "房号": "203",
    "面积（m²）": "122.10"
  },
  {
    "幢号": "1幢",
    "房号": "301",
    "面积（m²）": "124.32"
  },
  {
    "幢号": "1幢",
    "房号": "302",
    "面积（m²）": "123.71"
  },
  {
    "幢号": "1幢",
    "房号": "304",
    "面积（m²）": "122.71"
  },
  {
    "幢号": "1幢",
    "房号": "401",
    "面积（m²）": "124.32"
  },
  {
    "幢号": "1幢",
    "房号": "403",
    "面积（m²）": "122.10"
  },
  {
    "幢号": "1幢",
    "房号": "504",
    "面积（m²）": "122.71"
  },
  {
    "幢号": "1幢",
    "房号": "603",
    "面积（m²）": "122.10"
  },
  {
    "幢号": "1幢",
    "房号": "702",
    "面积（m²）": "123.71"
  },
  {
    "幢号": "1幢",
    "房号": "802",
    "面积（m²）": "123.71"
  },
  {
    "幢号": "1幢",
    "房号": "901",
    "面积（m²）": "124.32"
  },
  {
    "幢号": "1幢",
    "房号": "903",
    "面积（m²）": "122.10"
  },
  {
    "幢号": "1幢",
    "房号": "1001",
    "面积（m²）": "124.32"
  },
  {
    "幢号": "1幢",
    "房号": "1002",
    "面积（m²）": "123.71"
  },
  {
    "幢号": "1幢",
    "房号": "1004",
    "面积（m²）": "122.71"
  },
  {
    "幢号": "1幢",
    "房号": "1103",
    "面积（m²）": "122.10"
  },
  {
    "幢号": "1幢",
    "房号": "1104",
    "面积（m²）": "122.71"
  },
  {
    "幢号": "2幢",
    "房号": "102",
    "面积（m²）": "122.14"
  },
  {
    "幢号": "2幢",
    "房号": "103",
    "面积（m²）": "122.14"
  },
  {
    "幢号": "2幢",
    "房号": "201",
    "面积（m²）": "122.75"
  },
  {
    "幢号": "2幢",
    "房号": "301",
    "面积（m²）": "122.75"
  },
  {
    "幢号": "2幢",
    "房号": "302",
    "面积（m²）": "122.14"
  },
  {
    "幢号": "2幢",
    "房号": "402",
    "面积（m²）": "122.14"
  },
  {
    "幢号": "2幢",
    "房号": "403",
    "面积（m²）": "122.14"
  },
  {
    "幢号": "2幢",
    "房号": "501",
    "面积（m²）": "122.75"
  },
  {
    "幢号": "2幢",
    "房号": "502",
    "面积（m²）": "122.14"
  },
  {
    "幢号": "2幢",
    "房号": "503",
    "面积（m²）": "122.14"
  },
  {
    "幢号": "2幢",
    "房号": "504",
    "面积（m²）": "122.75"
  },
  {
    "幢号": "2幢",
    "房号": "601",
    "面积（m²）": "122.75"
  },
  {
    "幢号": "2幢",
    "房号": "603",
    "面积（m²）": "122.14"
  },
  {
    "幢号": "2幢",
    "房号": "604",
    "面积（m²）": "122.75"
  },
  {
    "幢号": "2幢",
    "房号": "803",
    "面积（m²）": "122.14"
  },
  {
    "幢号": "2幢",
    "房号": "804",
    "面积（m²）": "122.75"
  },
  {
    "幢号": "2幢",
    "房号": "902",
    "面积（m²）": "122.14"
  },
  {
    "幢号": "2幢",
    "房号": "903",
    "面积（m²）": "122.14"
  },
  {
    "幢号": "2幢",
    "房号": "904",
    "面积（m²）": "122.75"
  },
  {
    "幢号": "2幢",
    "房号": "1001",
    "面积（m²）": "122.75"
  },
  {
    "幢号": "2幢",
    "房号": "1101",
    "面积（m²）": "122.75"
  },
  {
    "幢号": "3幢",
    "房号": "101",
    "面积（m²）": "121.98"
  },
  {
    "幢号": "3幢",
    "房号": "102",
    "面积（m²）": "122.89"
  },
  {
    "幢号": "3幢",
    "房号": "201",
    "面积（m²）": "121.98"
  },
  {
    "幢号": "3幢",
    "房号": "302",
    "面积（m²）": "123.02"
  },
  {
    "幢号": "3幢",
    "房号": "501",
    "面积（m²）": "121.98"
  },
  {
    "幢号": "3幢",
    "房号": "601",
    "面积（m²）": "121.98"
  },
  {
    "幢号": "3幢",
    "房号": "602",
    "面积（m²）": "123.02"
  },
  {
    "幢号": "3幢",
    "房号": "701",
    "面积（m²）": "121.98"
  },
  {
    "幢号": "3幢",
    "房号": "702",
    "面积（m²）": "123.02"
  },
  {
    "幢号": "3幢",
    "房号": "901",
    "面积（m²）": "121.98"
  },
  {
    "幢号": "3幢",
    "房号": "902",
    "面积（m²）": "123.02"
  },
  {
    "幢号": "3幢",
    "房号": "1002",
    "面积（m²）": "123.02"
  },
  {
    "幢号": "4幢",
    "房号": "201",
    "面积（m²）": "125.27"
  },
  {
    "幢号": "4幢",
    "房号": "202",
    "面积（m²）": "124.57"
  },
  {
    "幢号": "4幢",
    "房号": "203",
    "面积（m²）": "124.57"
  },
  {
    "幢号": "4幢",
    "房号": "302",
    "面积（m²）": "124.57"
  },
  {
    "幢号": "4幢",
    "房号": "303",
    "面积（m²）": "124.57"
  },
  {
    "幢号": "4幢",
    "房号": "403",
    "面积（m²）": "124.57"
  },
  {
    "幢号": "4幢",
    "房号": "501",
    "面积（m²）": "125.27"
  },
  {
    "幢号": "4幢",
    "房号": "504",
    "面积（m²）": "125.19"
  },
  {
    "幢号": "4幢",
    "房号": "603",
    "面积（m²）": "124.57"
  },
  {
    "幢号": "4幢",
    "房号": "701",
    "面积（m²）": "125.27"
  },
  {
    "幢号": "4幢",
    "房号": "702",
    "面积（m²）": "124.57"
  },
  {
    "幢号": "4幢",
    "房号": "704",
    "面积（m²）": "125.19"
  },
  {
    "幢号": "4幢",
    "房号": "801",
    "面积（m²）": "125.27"
  },
  {
    "幢号": "4幢",
    "房号": "803",
    "面积（m²）": "124.57"
  },
  {
    "幢号": "4幢",
    "房号": "804",
    "面积（m²）": "125.19"
  },
  {
    "幢号": "4幢",
    "房号": "902",
    "面积（m²）": "124.57"
  },
  {
    "幢号": "4幢",
    "房号": "903",
    "面积（m²）": "124.57"
  },
  {
    "幢号": "4幢",
    "房号": "1002",
    "面积（m²）": "124.57"
  },
  {
    "幢号": "4幢",
    "房号": "1003",
    "面积（m²）": "124.57"
  },
  {
    "幢号": "4幢",
    "房号": "1004",
    "面积（m²）": "125.19"
  },
  {
    "幢号": "4幢",
    "房号": "1101",
    "面积（m²）": "125.27"
  },
  {
    "幢号": "4幢",
    "房号": "1102",
    "面积（m²）": "124.57"
  },
  {
    "幢号": "4幢",
    "房号": "1104",
    "面积（m²）": "125.19"
  },
  {
    "幢号": "5幢",
    "房号": "102",
    "面积（m²）": "139.35"
  },
  {
    "幢号": "5幢",
    "房号": "201",
    "面积（m²）": "139.35"
  },
  {
    "幢号": "5幢",
    "房号": "401",
    "面积（m²）": "139.35"
  },
  {
    "幢号": "5幢",
    "房号": "501",
    "面积（m²）": "139.35"
  },
  {
    "幢号": "5幢",
    "房号": "701",
    "面积（m²）": "139.35"
  },
  {
    "幢号": "5幢",
    "房号": "802",
    "面积（m²）": "139.35"
  },
  {
    "幢号": "5幢",
    "房号": "902",
    "面积（m²）": "139.35"
  },
  {
    "幢号": "5幢",
    "房号": "1002",
    "面积（m²）": "139.35"
  },
  {
    "幢号": "5幢",
    "房号": "1101",
    "面积（m²）": "139.35"
  },
  {
    "幢号": "5幢",
    "房号": "1102",
    "面积（m²）": "139.35"
  },
  {
    "幢号": "5幢",
    "房号": "1201",
    "面积（m²）": "139.35"
  },
  {
    "幢号": "5幢",
    "房号": "1202",
    "面积（m²）": "139.35"
  },
  {
    "幢号": "5幢",
    "房号": "1302",
    "面积（m²）": "139.35"
  },
  {
    "幢号": "5幢",
    "房号": "1502",
    "面积（m²）": "139.35"
  },
  {
    "幢号": "5幢",
    "房号": "1602",
    "面积（m²）": "139.35"
  },
  {
    "幢号": "5幢",
    "房号": "1701",
    "面积（m²）": "139.35"
  },
  {
    "幢号": "6幢",
    "房号": "102",
    "面积（m²）": "139.35"
  },
  {
    "幢号": "6幢",
    "房号": "202",
    "面积（m²）": "139.35"
  },
  {
    "幢号": "6幢",
    "房号": "301",
    "面积（m²）": "139.35"
  },
  {
    "幢号": "6幢",
    "房号": "402",
    "面积（m²）": "139.35"
  },
  {
    "幢号": "6幢",
    "房号": "502",
    "面积（m²）": "139.35"
  },
  {
    "幢号": "6幢",
    "房号": "601",
    "面积（m²）": "139.35"
  },
  {
    "幢号": "6幢",
    "房号": "602",
    "面积（m²）": "139.35"
  },
  {
    "幢号": "6幢",
    "房号": "701",
    "面积（m²）": "139.35"
  },
  {
    "幢号": "6幢",
    "房号": "702",
    "面积（m²）": "139.35"
  },
  {
    "幢号": "6幢",
    "房号": "801",
    "面积（m²）": "139.35"
  },
  {
    "幢号": "6幢",
    "房号": "802",
    "面积（m²）": "139.35"
  },
  {
    "幢号": "6幢",
    "房号": "901",
    "面积（m²）": "139.35"
  },
  {
    "幢号": "6幢",
    "房号": "1002",
    "面积（m²）": "139.35"
  },
  {
    "幢号": "6幢",
    "房号": "1102",
    "面积（m²）": "139.35"
  },
  {
    "幢号": "6幢",
    "房号": "1202",
    "面积（m²）": "139.35"
  },
  {
    "幢号": "6幢",
    "房号": "1301",
    "面积（m²）": "139.35"
  },
  {
    "幢号": "6幢",
    "房号": "1502",
    "面积（m²）": "139.35"
  },
  {
    "幢号": "6幢",
    "房号": "1602",
    "面积（m²）": "139.35"
  },
  {
    "幢号": "6幢",
    "房号": "1701",
    "面积（m²）": "139.35"
  },
  {
    "幢号": "7幢",
    "房号": "102",
    "面积（m²）": "139.35"
  },
  {
    "幢号": "7幢",
    "房号": "202",
    "面积（m²）": "139.35"
  },
  {
    "幢号": "7幢",
    "房号": "301",
    "面积（m²）": "139.35"
  },
  {
    "幢号": "7幢",
    "房号": "402",
    "面积（m²）": "139.35"
  },
  {
    "幢号": "7幢",
    "房号": "501",
    "面积（m²）": "139.35"
  },
  {
    "幢号": "7幢",
    "房号": "502",
    "面积（m²）": "139.35"
  },
  {
    "幢号": "7幢",
    "房号": "601",
    "面积（m²）": "139.35"
  },
  {
    "幢号": "7幢",
    "房号": "602",
    "面积（m²）": "139.35"
  },
  {
    "幢号": "7幢",
    "房号": "702",
    "面积（m²）": "139.35"
  },
  {
    "幢号": "7幢",
    "房号": "801",
    "面积（m²）": "139.35"
  },
  {
    "幢号": "7幢",
    "房号": "901",
    "面积（m²）": "139.35"
  },
  {
    "幢号": "7幢",
    "房号": "1002",
    "面积（m²）": "139.35"
  },
  {
    "幢号": "7幢",
    "房号": "1102",
    "面积（m²）": "139.35"
  },
  {
    "幢号": "7幢",
    "房号": "1201",
    "面积（m²）": "139.35"
  },
  {
    "幢号": "7幢",
    "房号": "1202",
    "面积（m²）": "139.35"
  },
  {
    "幢号": "7幢",
    "房号": "1301",
    "面积（m²）": "139.35"
  },
  {
    "幢号": "7幢",
    "房号": "1502",
    "面积（m²）": "139.35"
  },
  {
    "幢号": "7幢",
    "房号": "1601",
    "面积（m²）": "139.35"
  },
  {
    "幢号": "7幢",
    "房号": "1602",
    "面积（m²）": "139.35"
  },
  {
    "幢号": "7幢",
    "房号": "1702",
    "面积（m²）": "139.35"
  },
  {
    "幢号": "8幢",
    "房号": "102",
    "面积（m²）": "139.35"
  },
  {
    "幢号": "8幢",
    "房号": "201",
    "面积（m²）": "139.35"
  },
  {
    "幢号": "8幢",
    "房号": "301",
    "面积（m²）": "139.35"
  },
  {
    "幢号": "8幢",
    "房号": "402",
    "面积（m²）": "139.35"
  },
  {
    "幢号": "8幢",
    "房号": "502",
    "面积（m²）": "139.35"
  },
  {
    "幢号": "8幢",
    "房号": "601",
    "面积（m²）": "139.35"
  },
  {
    "幢号": "8幢",
    "房号": "701",
    "面积（m²）": "139.35"
  },
  {
    "幢号": "8幢",
    "房号": "702",
    "面积（m²）": "139.35"
  },
  {
    "幢号": "8幢",
    "房号": "801",
    "面积（m²）": "139.35"
  },
  {
    "幢号": "8幢",
    "房号": "901",
    "面积（m²）": "139.35"
  },
  {
    "幢号": "8幢",
    "房号": "902",
    "面积（m²）": "139.35"
  },
  {
    "幢号": "8幢",
    "房号": "1002",
    "面积（m²）": "139.35"
  },
  {
    "幢号": "8幢",
    "房号": "1201",
    "面积（m²）": "139.35"
  },
  {
    "幢号": "8幢",
    "房号": "1502",
    "面积（m²）": "139.35"
  },
  {
    "幢号": "8幢",
    "房号": "1601",
    "面积（m²）": "139.35"
  },
  {
    "幢号": "8幢",
    "房号": "1702",
    "面积（m²）": "139.35"
  },
  {
    "幢号": "9幢",
    "房号": "201",
    "面积（m²）": "139.35"
  },
  {
    "幢号": "9幢",
    "房号": "302",
    "面积（m²）": "139.35"
  },
  {
    "幢号": "9幢",
    "房号": "402",
    "面积（m²）": "139.35"
  },
  {
    "幢号": "9幢",
    "房号": "501",
    "面积（m²）": "139.35"
  },
  {
    "幢号": "9幢",
    "房号": "502",
    "面积（m²）": "139.35"
  },
  {
    "幢号": "9幢",
    "房号": "602",
    "面积（m²）": "139.35"
  },
  {
    "幢号": "9幢",
    "房号": "702",
    "面积（m²）": "139.35"
  },
  {
    "幢号": "9幢",
    "房号": "1002",
    "面积（m²）": "139.35"
  },
  {
    "幢号": "9幢",
    "房号": "1202",
    "面积（m²）": "139.35"
  },
  {
    "幢号": "9幢",
    "房号": "1301",
    "面积（m²）": "139.35"
  },
  {
    "幢号": "9幢",
    "房号": "1302",
    "面积（m²）": "139.35"
  },
  {
    "幢号": "9幢",
    "房号": "1401",
    "面积（m²）": "139.35"
  },
  {
    "幢号": "9幢",
    "房号": "1601",
    "面积（m²）": "139.35"
  },
  {
    "幢号": "9幢",
    "房号": "1701",
    "面积（m²）": "139.35"
  },
  {
    "幢号": "9幢",
    "房号": "1702",
    "面积（m²）": "139.35"
  },
  {
    "幢号": "10幢",
    "房号": "202",
    "面积（m²）": "139.35"
  },
  {
    "幢号": "10幢",
    "房号": "302",
    "面积（m²）": "139.35"
  },
  {
    "幢号": "10幢",
    "房号": "501",
    "面积（m²）": "139.35"
  },
  {
    "幢号": "10幢",
    "房号": "602",
    "面积（m²）": "139.35"
  },
  {
    "幢号": "10幢",
    "房号": "702",
    "面积（m²）": "139.35"
  },
  {
    "幢号": "10幢",
    "房号": "802",
    "面积（m²）": "139.35"
  },
  {
    "幢号": "10幢",
    "房号": "1001",
    "面积（m²）": "139.35"
  },
  {
    "幢号": "10幢",
    "房号": "1101",
    "面积（m²）": "139.35"
  },
  {
    "幢号": "10幢",
    "房号": "1202",
    "面积（m²）": "139.35"
  },
  {
    "幢号": "10幢",
    "房号": "1302",
    "面积（m²）": "139.35"
  },
  {
    "幢号": "10幢",
    "房号": "1501",
    "面积（m²）": "139.35"
  },
  {
    "幢号": "10幢",
    "房号": "1601",
    "面积（m²）": "139.35"
  },
  {
    "幢号": "10幢",
    "房号": "1602",
    "面积（m²）": "139.35"
  },
  {
    "幢号": "10幢",
    "房号": "1701",
    "面积（m²）": "139.35"
  },
  {
    "幢号": "11幢",
    "房号": "101",
    "面积（m²）": "120.56"
  },
  {
    "幢号": "11幢",
    "房号": "202",
    "面积（m²）": "139.40"
  },
  {
    "幢号": "11幢",
    "房号": "402",
    "面积（m²）": "139.40"
  },
  {
    "幢号": "11幢",
    "房号": "501",
    "面积（m²）": "139.40"
  },
  {
    "幢号": "11幢",
    "房号": "602",
    "面积（m²）": "139.40"
  },
  {
    "幢号": "11幢",
    "房号": "801",
    "面积（m²）": "139.40"
  },
  {
    "幢号": "11幢",
    "房号": "901",
    "面积（m²）": "139.40"
  },
  {
    "幢号": "11幢",
    "房号": "1001",
    "面积（m²）": "139.40"
  },
  {
    "幢号": "11幢",
    "房号": "1102",
    "面积（m²）": "139.40"
  },
  {
    "幢号": "11幢",
    "房号": "1301",
    "面积（m²）": "139.40"
  },
  {
    "幢号": "11幢",
    "房号": "1302",
    "面积（m²）": "139.40"
  },
  {
    "幢号": "11幢",
    "房号": "1401",
    "面积（m²）": "139.40"
  },
  {
    "幢号": "11幢",
    "房号": "1402",
    "面积（m²）": "139.40"
  },
  {
    "幢号": "11幢",
    "房号": "1501",
    "面积（m²）": "139.40"
  },
  {
    "幢号": "11幢",
    "房号": "1502",
    "面积（m²）": "139.40"
  },
  {
    "幢号": "11幢",
    "房号": "1701",
    "面积（m²）": "139.40"
  },
  {
    "幢号": "12幢",
    "房号": "202",
    "面积（m²）": "108.22"
  },
  {
    "幢号": "12幢",
    "房号": "204",
    "面积（m²）": "108.22"
  },
  {
    "幢号": "12幢",
    "房号": "302",
    "面积（m²）": "108.22"
  },
  {
    "幢号": "12幢",
    "房号": "501",
    "面积（m²）": "108.27"
  },
  {
    "幢号": "12幢",
    "房号": "502",
    "面积（m²）": "108.22"
  },
  {
    "幢号": "12幢",
    "房号": "604",
    "面积（m²）": "108.22"
  },
  {
    "幢号": "12幢",
    "房号": "702",
    "面积（m²）": "108.22"
  },
  {
    "幢号": "12幢",
    "房号": "703",
    "面积（m²）": "108.22"
  },
  {
    "幢号": "12幢",
    "房号": "801",
    "面积（m²）": "108.27"
  },
  {
    "幢号": "12幢",
    "房号": "804",
    "面积（m²）": "108.22"
  },
  {
    "幢号": "12幢",
    "房号": "902",
    "面积（m²）": "108.22"
  },
  {
    "幢号": "12幢",
    "房号": "1002",
    "面积（m²）": "108.22"
  },
  {
    "幢号": "12幢",
    "房号": "1004",
    "面积（m²）": "108.22"
  },
  {
    "幢号": "12幢",
    "房号": "1101",
    "面积（m²）": "108.27"
  },
  {
    "幢号": "12幢",
    "房号": "1103",
    "面积（m²）": "108.22"
  },
  {
    "幢号": "12幢",
    "房号": "1104",
    "面积（m²）": "108.22"
  },
  {
    "幢号": "12幢",
    "房号": "1201",
    "面积（m²）": "108.27"
  },
  {
    "幢号": "12幢",
    "房号": "1203",
    "面积（m²）": "108.22"
  },
  {
    "幢号": "12幢",
    "房号": "1301",
    "面积（m²）": "108.27"
  },
  {
    "幢号": "12幢",
    "房号": "1302",
    "面积（m²）": "108.22"
  },
  {
    "幢号": "12幢",
    "房号": "1304",
    "面积（m²）": "108.22"
  },
  {
    "幢号": "12幢",
    "房号": "1401",
    "面积（m²）": "108.27"
  },
  {
    "幢号": "12幢",
    "房号": "1404",
    "面积（m²）": "108.22"
  },
  {
    "幢号": "12幢",
    "房号": "1503",
    "面积（m²）": "108.22"
  },
  {
    "幢号": "12幢",
    "房号": "1504",
    "面积（m²）": "108.22"
  },
  {
    "幢号": "12幢",
    "房号": "1603",
    "面积（m²）": "108.22"
  },
  {
    "幢号": "12幢",
    "房号": "1604",
    "面积（m²）": "108.22"
  },
  {
    "幢号": "12幢",
    "房号": "1702",
    "面积（m²）": "108.22"
  },
  {
    "幢号": "12幢",
    "房号": "1704",
    "面积（m²）": "108.22"
  },
  {
    "幢号": "12幢",
    "房号": "1802",
    "面积（m²）": "108.22"
  },
  {
    "幢号": "12幢",
    "房号": "1803",
    "面积（m²）": "108.22"
  },
  {
    "幢号": "12幢",
    "房号": "1804",
    "面积（m²）": "108.22"
  },
  {
    "幢号": "12幢",
    "房号": "1902",
    "面积（m²）": "108.22"
  },
  {
    "幢号": "12幢",
    "房号": "2001",
    "面积（m²）": "108.27"
  },
  {
    "幢号": "12幢",
    "房号": "2002",
    "面积（m²）": "108.22"
  },
  {
    "幢号": "12幢",
    "房号": "2003",
    "面积（m²）": "108.22"
  },
  {
    "幢号": "12幢",
    "房号": "2004",
    "面积（m²）": "108.22"
  },
  {
    "幢号": "12幢",
    "房号": "2201",
    "面积（m²）": "108.27"
  },
  {
    "幢号": "12幢",
    "房号": "2202",
    "面积（m²）": "108.22"
  },
  {
    "幢号": "12幢",
    "房号": "2203",
    "面积（m²）": "108.22"
  },
  {
    "幢号": "12幢",
    "房号": "2204",
    "面积（m²）": "108.22"
  },
  {
    "幢号": "12幢",
    "房号": "2301",
    "面积（m²）": "108.27"
  },
  {
    "幢号": "12幢",
    "房号": "2302",
    "面积（m²）": "108.22"
  },
  {
    "幢号": "12幢",
    "房号": "2304",
    "面积（m²）": "108.22"
  },
  {
    "幢号": "13幢",
    "房号": "201",
    "面积（m²）": "108.83"
  },
  {
    "幢号": "13幢",
    "房号": "202",
    "面积（m²）": "108.84"
  },
  {
    "幢号": "13幢",
    "房号": "204",
    "面积（m²）": "108.80"
  },
  {
    "幢号": "13幢",
    "房号": "302",
    "面积（m²）": "108.84"
  },
  {
    "幢号": "13幢",
    "房号": "401",
    "面积（m²）": "108.83"
  },
  {
    "幢号": "13幢",
    "房号": "402",
    "面积（m²）": "108.84"
  },
  {
    "幢号": "13幢",
    "房号": "404",
    "面积（m²）": "108.80"
  },
  {
    "幢号": "13幢",
    "房号": "501",
    "面积（m²）": "108.83"
  },
  {
    "幢号": "13幢",
    "房号": "503",
    "面积（m²）": "108.84"
  },
  {
    "幢号": "13幢",
    "房号": "504",
    "面积（m²）": "108.80"
  },
  {
    "幢号": "13幢",
    "房号": "601",
    "面积（m²）": "108.83"
  },
  {
    "幢号": "13幢",
    "房号": "602",
    "面积（m²）": "108.84"
  },
  {
    "幢号": "13幢",
    "房号": "603",
    "面积（m²）": "108.84"
  },
  {
    "幢号": "13幢",
    "房号": "701",
    "面积（m²）": "108.83"
  },
  {
    "幢号": "13幢",
    "房号": "704",
    "面积（m²）": "108.80"
  },
  {
    "幢号": "13幢",
    "房号": "802",
    "面积（m²）": "108.84"
  },
  {
    "幢号": "13幢",
    "房号": "804",
    "面积（m²）": "108.80"
  },
  {
    "幢号": "13幢",
    "房号": "901",
    "面积（m²）": "108.83"
  },
  {
    "幢号": "13幢",
    "房号": "902",
    "面积（m²）": "108.84"
  },
  {
    "幢号": "13幢",
    "房号": "903",
    "面积（m²）": "108.84"
  },
  {
    "幢号": "13幢",
    "房号": "1001",
    "面积（m²）": "108.83"
  },
  {
    "幢号": "13幢",
    "房号": "1003",
    "面积（m²）": "108.84"
  },
  {
    "幢号": "13幢",
    "房号": "1004",
    "面积（m²）": "108.80"
  },
  {
    "幢号": "13幢",
    "房号": "1102",
    "面积（m²）": "108.84"
  },
  {
    "幢号": "13幢",
    "房号": "1104",
    "面积（m²）": "108.80"
  },
  {
    "幢号": "13幢",
    "房号": "1201",
    "面积（m²）": "108.83"
  },
  {
    "幢号": "13幢",
    "房号": "1202",
    "面积（m²）": "108.84"
  },
  {
    "幢号": "13幢",
    "房号": "1203",
    "面积（m²）": "108.84"
  },
  {
    "幢号": "13幢",
    "房号": "1204",
    "面积（m²）": "108.80"
  },
  {
    "幢号": "13幢",
    "房号": "1401",
    "面积（m²）": "108.83"
  },
  {
    "幢号": "13幢",
    "房号": "1402",
    "面积（m²）": "108.84"
  },
  {
    "幢号": "13幢",
    "房号": "1404",
    "面积（m²）": "108.80"
  },
  {
    "幢号": "13幢",
    "房号": "1503",
    "面积（m²）": "108.84"
  },
  {
    "幢号": "13幢",
    "房号": "1504",
    "面积（m²）": "108.80"
  },
  {
    "幢号": "13幢",
    "房号": "1702",
    "面积（m²）": "108.84"
  },
  {
    "幢号": "13幢",
    "房号": "1704",
    "面积（m²）": "108.80"
  },
  {
    "幢号": "13幢",
    "房号": "1803",
    "面积（m²）": "108.84"
  },
  {
    "幢号": "13幢",
    "房号": "1902",
    "面积（m²）": "108.84"
  },
  {
    "幢号": "13幢",
    "房号": "1903",
    "面积（m²）": "108.84"
  },
  {
    "幢号": "16、17幢",
    "房号": "2_301",
    "面积（m²）": "169.27"
  },
  {
    "幢号": "16、17幢",
    "房号": "2_502",
    "面积（m²）": "169.25"
  },
  {
    "幢号": "16、17幢",
    "房号": "2_601",
    "面积（m²）": "169.27"
  },
  {
    "幢号": "16、17幢",
    "房号": "2_602",
    "面积（m²）": "169.25"
  },
  {
    "幢号": "16、17幢",
    "房号": "2_702",
    "面积（m²）": "169.25"
  },
  {
    "幢号": "16、17幢",
    "房号": "2_801",
    "面积（m²）": "169.27"
  },
  {
    "幢号": "16、17幢",
    "房号": "2_901",
    "面积（m²）": "169.27"
  },
  {
    "幢号": "16、17幢",
    "房号": "2_1002",
    "面积（m²）": "169.25"
  },
  {
    "幢号": "16、17幢",
    "房号": "2_1101",
    "面积（m²）": "169.27"
  },
  {
    "幢号": "16、17幢",
    "房号": "2_1201",
    "面积（m²）": "169.27"
  },
  {
    "幢号": "16、17幢",
    "房号": "2_1202",
    "面积（m²）": "169.25"
  },
  {
    "幢号": "18、19幢",
    "房号": "1_401",
    "面积（m²）": "171.39"
  },
  {
    "幢号": "18、19幢",
    "房号": "1_402",
    "面积（m²）": "171.43"
  },
  {
    "幢号": "18、19幢",
    "房号": "1_501",
    "面积（m²）": "171.39"
  },
  {
    "幢号": "18、19幢",
    "房号": "1_601",
    "面积（m²）": "171.39"
  },
  {
    "幢号": "18、19幢",
    "房号": "1_701",
    "面积（m²）": "171.39"
  },
  {
    "幢号": "18、19幢",
    "房号": "1_901",
    "面积（m²）": "171.39"
  },
  {
    "幢号": "18、19幢",
    "房号": "1_1001",
    "面积（m²）": "171.39"
  },
  {
    "幢号": "18、19幢",
    "房号": "1_1002",
    "面积（m²）": "171.43"
  },
  {
    "幢号": "18、19幢",
    "房号": "1_1201",
    "面积（m²）": "171.39"
  },
  {
    "幢号": "18、19幢",
    "房号": "1_1202",
    "面积（m²）": "171.43"
  }
]